liminal/.gitignore
liminal/.lock
liminal/CACHEDIR.TAG
liminal/__init__.py
liminal/mappers.py
liminal/py.typed
liminal/pyvenv.cfg
liminal/utils.py
liminal/base/base_dropdown.py
liminal/base/base_operation.py
liminal/base/base_validation_filters.py
liminal/base/compare_operation.py
liminal/base/name_template_parts.py
liminal/base/str_enum.py
liminal/base/properties/base_field_properties.py
liminal/base/properties/base_name_template.py
liminal/base/properties/base_schema_properties.py
liminal/cli/cli.py
liminal/cli/controller.py
liminal/cli/live_test_dropdown_migration.py
liminal/cli/live_test_entity_schema_migration.py
liminal/cli/utils.py
liminal/connection/__init__.py
liminal/connection/benchling_connection.py
liminal/connection/benchling_service.py
liminal/dropdowns/api.py
liminal/dropdowns/compare.py
liminal/dropdowns/generate_files.py
liminal/dropdowns/operations.py
liminal/dropdowns/utils.py
liminal/entity_schemas/api.py
liminal/entity_schemas/compare.py
liminal/entity_schemas/entity_schema_models.py
liminal/entity_schemas/generate_files.py
liminal/entity_schemas/operations.py
liminal/entity_schemas/tag_schema_models.py
liminal/entity_schemas/utils.py
liminal/enums/__init__.py
liminal/enums/benchling_api_field_type.py
liminal/enums/benchling_entity_type.py
liminal/enums/benchling_field_type.py
liminal/enums/benchling_folder_item_type.py
liminal/enums/benchling_naming_strategy.py
liminal/enums/benchling_sequence_type.py
liminal/enums/name_template_part_type.py
liminal/enums/sequence_constraint.py
liminal/external/__init__.py
liminal/migrate/components.py
liminal/migrate/revision.py
liminal/migrate/revisions_timeline.py
liminal/orm/base.py
liminal/orm/base_model.py
liminal/orm/base_results_model.py
liminal/orm/column.py
liminal/orm/mixins.py
liminal/orm/name_template.py
liminal/orm/name_template_parts.py
liminal/orm/relationship.py
liminal/orm/results_schema_properties.py
liminal/orm/schema_properties.py
liminal/orm/base_tables/registry_entity.py
liminal_orm-4.4.4.dist-info/METADATA
liminal_orm-4.4.4.dist-info/WHEEL
liminal_orm-4.4.4.dist-info/entry_points.txt
liminal_orm-4.4.4.dist-info/licenses/LICENSE.md
liminal_orm-4.4.4.dist-info/RECORD
