Metadata-Version: 2.4
Name: liminal-orm
Version: 4.4.4
Summary: An ORM and toolkit that builds on top of Benchling's platform to keep your schemas and downstream code dependencies in sync.
Project-URL: Homepage, https://github.com/dynotx/liminal-orm
Project-URL: Repository, https://github.com/dynotx/liminal-orm
Project-URL: Documentation, https://dynotx.github.io/liminal-orm/
Project-URL: Bug Tracker, https://github.com/dynotx/liminal-orm/issues
Author-email: DynoTx Open Source <opensource@dynotx.com>
License-File: LICENSE.md
Requires-Python: <4,>=3.9
Requires-Dist: benchling-sdk<2,>=1.21.2
Requires-Dist: bs4<0.0.3,>=0.0.2
Requires-Dist: click<8.2.0,>=8.0.0
Requires-Dist: lxml<6,>=5.3.0
Requires-Dist: numpy<2,>=1.23.5
Requires-Dist: pandas<3,>=1.5.3
Requires-Dist: psycopg2-binary<3,>=2.9.10
Requires-Dist: pydantic<=2.11,>=2
Requires-Dist: requests<3,>=2.32.3
Requires-Dist: rich<14,>=13.9.2
Requires-Dist: sqlalchemy<2
Requires-Dist: tenacity<10,>=8
Requires-Dist: tornado==6.5.0
Requires-Dist: typer<0.13,>=0.12.5
